AUTHORS
CODE_OF_CONDUCT.md
CONTRIBUTING.rst
HACKING.rst
LICENSE
MANIFEST.in
NOTICE
README.rst
SUPPORT.rst
setup.py
conf/cloud
conf/cloud.profiles
conf/cloud.providers
conf/master
conf/minion
conf/proxy
conf/roster
conf/cloud.maps.d/cloud.map
conf/cloud.maps.d/saltify.map
conf/cloud.profiles.d/EC2-us-east-1.profiles
conf/cloud.profiles.d/EC2-us-west-1.profiles
conf/cloud.profiles.d/EC2-us-west-2.profiles
conf/cloud.profiles.d/saltify.conf
conf/cloud.profiles.d/tencentcloud-guangzhou-s1sm1.profiles
conf/cloud.providers.d/digitalocean.conf
conf/cloud.providers.d/ec2.conf
conf/cloud.providers.d/gogrid.conf
conf/cloud.providers.d/ibmsce.conf
conf/cloud.providers.d/joyent.conf
conf/cloud.providers.d/linode.conf
conf/cloud.providers.d/parallels.conf
conf/cloud.providers.d/proxmox.conf
conf/cloud.providers.d/saltify.conf
conf/cloud.providers.d/scaleway.conf
conf/cloud.providers.d/tencent.conf
conf/cloud.providers.d/vsphere.conf
conf/suse/master
doc/Makefile
doc/apidoc-saltmods.sh
doc/conf.py
doc/contents.rst
doc/faq.rst
doc/favicon.ico
doc/gen_gource
doc/glossary.rst
doc/spelling_wordlist.txt
doc/.scripts/setup-transifex-config
doc/_ext/httpdomain.py
doc/_ext/saltautodoc.py
doc/_ext/saltdomain.py
doc/_ext/saltrepo.py
doc/_ext/shorturls.py
doc/_ext/youtube.py
doc/_incl/extend_with_require_watch.rst
doc/_incl/requisite_incl.rst
doc/_incl/_incl/sls_filename_cant_contain_period.rst
doc/_static/cloud-settings-inheritance.png
doc/_static/external-job-cache.png
doc/_static/favicon.ico
doc/_static/master-job-cache.png
doc/_static/napalm_logo.png
doc/_static/proxy_minions.drawio.xml
doc/_static/proxy_minions.png
doc/_static/proxy_minions.svg
doc/_static/rest_status_screen.png
doc/_static/salt-logo-full.svg
doc/_static/salt-logo.pdf
doc/_static/salt-logo.png
doc/_static/salt-logo.svg
doc/_static/snapshot_manager.png
doc/_static/spm-overview.png
doc/_static/spm-package-contents.png
doc/_static/spm-package-extraction.png
doc/_templates/404.html
doc/_templates/autosummary.rst.tmpl
salt_ssh.egg-info/PKG-INFO
salt_ssh.egg-info/SOURCES.txt
salt_ssh.egg-info/dependency_links.txt
salt_ssh.egg-info/entry_points.txt
salt_ssh.egg-info/not-zip-safe
salt_ssh.egg-info/requires.txt
salt_ssh.egg-info/top_level.txt
