Metadata-Version: 2.1
Name: salt-ssh
Version: 3000.9
Summary: Portable, distributed, remote execution and configuration management system
Home-page: http://saltstack.org
Author: Thomas S Hatch
Author-email: thatch45@gmail.com
License: Apache Software License 2.0
Platform: UNKNOWN
